mcbackend/__init__.py
mcbackend/core.py
mcbackend/meta.py
mcbackend/py.typed
mcbackend/test_backend_clickhouse.py
mcbackend/test_backend_null.py
mcbackend/test_backend_numpy.py
mcbackend/test_core.py
mcbackend/test_npproto.py
mcbackend/test_utils.py
mcbackend/utils.py
mcbackend/backends/__init__.py
mcbackend/backends/clickhouse.py
mcbackend/backends/null.py
mcbackend/backends/numpy.py
mcbackend/npproto/__init__.py
mcbackend/npproto/utils.py
mcbackend-0.5.3.dist-info/LICENSE
mcbackend-0.5.3.dist-info/METADATA
mcbackend-0.5.3.dist-info/WHEEL
mcbackend-0.5.3.dist-info/top_level.txt
mcbackend-0.5.3.dist-info/RECORD
