Metadata-Version: 2.1
Name: mcbackend
Version: 0.5.3
Summary: Framework agnostic backends for MCMC sample storage
Home-page: https://github.com/michaelosthege/mcbackend
Author: Michael Osthege
Author-email: michael.osthege@outlook.com
License: AGPLv3
Classifier: Programming Language :: Python
Classifier: Operating System :: OS Independent
Classifier: License :: OSI Approved :: GNU Affero General Public License v3
Classifier: Intended Audience :: Science/Research
Requires-Python: >=3.7
License-File: LICENSE
Requires-Dist: betterproto==2.0.0b7
Requires-Dist: hagelkorn
Requires-Dist: numpy
Requires-Dist: pandas
